[
  {
    "Project Name": "Basanti Enclave",
    "Promoter Name": "M/S. NEELACHAL INFRA DEVELOPERS PVT. LTD",
    "Rera Regd. No": "RP/01/2025/01362",
    "Project Address": "Angul",
    "Project Type": "Residential",
    "Started From": "May, 2025",
    "Possession by": "Dec, 2027",
    "Units": "86 Units",
    "GST No.": "21AADCN5439J2ZH",
    "Address of the Promoter": "Gurudwara, PO-South Balanda, Via: Talcher Rural INR, Angul-759116, Dist. Angul, Odisha ,,,,,"
  },
  {
    "Project Name": "UDYAYEEN",
    "Promoter Name": "SHYAMCHAND BUILDERS PRIVATE LIMITED",
    "Rera Regd. No": "RP/19/2025/01361",
    "Project Address": "Khordha",
    "Project Type": "Residential",
    "Started From": "May, 2025",
    "Possession by": "Dec, 2027",
    "Units": "54 Units",
    "GST No.": "21ABCCS4755J1ZB",
    "Address of the Promoter": "MIG-II 21/2 Ground Floor,Chandrasekharpur,Bhubaneswar,Khordha,Odisha,751016"
  },
  {
    "Project Name": "BARSANA RESIDENCY - II",
    "Promoter Name": "RITA PODDAR",
    "Rera Regd. No": "PS/28/2025/01360",
    "Project Address": "Sambalpur",
    "Project Type": "Plotted Scheme",
    "Started From": "May, 2025",
    "Possession by": "Mar, 2028",
    "Units": "8 Units",
    "GST No.": "21AREPP3171E1Z7",
    "Address of the Promoter": "N/A"
  },
  {
    "Project Name": "KRISHNA MANOR PH-II",
    "Promoter Name": "KRISHNA PROPERTIES & DEVELOPERS PRIVATE LIMITED",
    "Rera Regd. No": "PS/7/2025/01358",
    "Project Address": "Cuttack",
    "Project Type": "Plotted Scheme",
    "Started From": "May, 2025",
    "Possession by": "Feb, 2028",
    "Units": "24 Units",
    "GST No.": "21AAECK8663L2Z7",
    "Address of the Promoter": "Plot No-46, Indraprastha Housing Colony, Phase-II, Pokhariput, Bhubaneswar, Khordha, Odisha-751020.,,,,,"
  },
  {
    "Project Name": "BHAVYAVILLA",
    "Promoter Name": "SUNSHINE INFRATECH",
    "Rera Regd. No": "PS/19/2025/01351",
    "Project Address": "Khordha",
    "Project Type": "Plotted Scheme",
    "Started From": "May, 2025",
    "Possession by": "Jun, 2025",
    "Units": "12 Units",
    "GST No.": "21ACMFS3976P1ZC",
    "Address of the Promoter": "PLOT NO 339,GOUTAMNAGAR,BJB NAGAR,Khordha,Odisha,751014"
  },
  {
    "Project Name": "MURALIDHARA HEIGHTS",
    "Promoter Name": "TRILOCHAN PROJECTS AND DEVELOPERS PVT. LTD",
    "Rera Regd. No": "RP/19/2025/01355",
    "Project Address": "Khordha",
    "Project Type": "Residential",
    "Started From": "May, 2025",
    "Possession by": "Nov, 2027",
    "Units": "38 Units",
    "GST No.": "21AAGCT0547E1ZT",
    "Address of the Promoter": "Plot No-208, Flat No-301,Trilochan Plaza,Saheed Nagar,Bhubaneswer,Khordha,Odisha,751007"
  }
]